vkid/__init__.py
vkid-0.1.dist-info/LICENSE.txt
vkid-0.1.dist-info/METADATA
vkid-0.1.dist-info/WHEEL
vkid-0.1.dist-info/top_level.txt
vkid-0.1.dist-info/RECORD
