Metadata-Version: 2.1
Name: vkid
Version: 0.1
Summary: VK ID API
Author: 
Author-email: 
Classifier: Programming Language :: Python :: 3
Classifier: License :: OSI Approved :: MIT License
Classifier: Operating System :: OS Independent
License-File: LICENSE.txt
